{
	"id": "980b7f30-3fa0-40ca-8459-bdad0fffc985",
	"name": "TesteYaman",
	"description": "",
	"auth": null,
	"events": null,
	"variables": [],
	"order": [
		"87ff4e4e-f775-4d13-b132-cf3ba5033bff"
	],
	"folders_order": [],
	"protocolProfileBehavior": {},
	"folders": [],
	"requests": [
		{
			"id": "87ff4e4e-f775-4d13-b132-cf3ba5033bff",
			"name": "https://api.trello.com/1/actions/592f11060f95a3d3d46a987a",
			"url": "https://api.trello.com/1/actions/592f11060f95a3d3d46a987a",
			"description": "",
			"data": [],
			"dataOptions": {
				"raw": {
					"language": "json"
				}
			},
			"dataMode": "raw",
			"headerData": null,
			"method": "GET",
			"pathVariableData": [],
			"queryParams": [],
			"auth": null,
			"events": null,
			"folder": null,
			"protocolProfileBehavior": {
				"disableBodyPruning": true
			},
			"rawModeData": "",
			"pathVariables": {}
		}
	]
}